mtsb/__init__.py
mtsb/mtsb.py
mtsb-0.0.7.dist-info/LICENSE
mtsb-0.0.7.dist-info/METADATA
mtsb-0.0.7.dist-info/WHEEL
mtsb-0.0.7.dist-info/top_level.txt
mtsb-0.0.7.dist-info/RECORD
