Metadata-Version: 2.1
Name: mtsb
Version: 0.0.7
Summary: Python library that collects tweets about movies, performs a sentiment analysis and correlates it with the boxoffice result of the 7 days after the movie release.
Home-page: https://github.com/federicodeservi/mtsb
Author: Federico De Servi, Alessandro Pontini
Author-email: federico@federicodeservi.com, a.pontini1@campus.unimib.it
License: MIT
Platform: UNKNOWN
Classifier: Development Status :: 4 - Beta
Classifier: Natural Language :: English
Classifier: License :: OSI Approved :: MIT License
Classifier: Programming Language :: Python
Classifier: Programming Language :: Python :: 3.5
Classifier: Programming Language :: Python :: 3.6
Classifier: Programming Language :: Python :: 3.7
Classifier: Topic :: Software Development :: Libraries
Classifier: Topic :: Software Development :: Libraries :: Python Modules
Classifier: Intended Audience :: Developers
Requires-Python: >=3.5
Requires-Dist: numpy
Requires-Dist: pandas
Requires-Dist: beautifulsoup4
Requires-Dist: imdbpy
Requires-Dist: lxml
Requires-Dist: tweepy
Requires-Dist: kafka
Requires-Dist: pymongo
Requires-Dist: pprint
Requires-Dist: contractions
Requires-Dist: inflect
Requires-Dist: ntlk
Requires-Dist: google-cloud-language
Requires-Dist: html5lib
Requires-Dist: mime
